admin_site_search/__init__.py
admin_site_search/apps.py
admin_site_search/views.py
admin_site_search/static/admin_site_search/search.js
admin_site_search/static/admin_site_search/style.css
admin_site_search/static/admin_site_search/alpinejs/3-12-0.min.js
admin_site_search/static/admin_site_search/alpinejs/focus-3-12-0.min.js
admin_site_search/templates/admin_site_search/button.html
admin_site_search/templates/admin_site_search/head.html
admin_site_search/templates/admin_site_search/icon.html
admin_site_search/templates/admin_site_search/input.html
admin_site_search/templates/admin_site_search/modal.html
admin_site_search/templates/admin_site_search/results.html
admin_site_search/templates/admin_site_search/spinner.html
django_admin_site_search-1.1.0.dist-info/LICENSE
django_admin_site_search-1.1.0.dist-info/METADATA
django_admin_site_search-1.1.0.dist-info/WHEEL
django_admin_site_search-1.1.0.dist-info/top_level.txt
django_admin_site_search-1.1.0.dist-info/RECORD
