Metadata-Version: 2.1
Name: django-admin-site-search
Version: 1.1.0
Summary: A search (cmd+k) modal, for the Django admin UI, that searches your entire site.
Home-page: https://github.com/ahmedaljawahiry/django-admin-site-search/
Author: Ahmed Al-Jawahiry
Author-email: ahmedaljawahiry@gmail.com
License: MIT
Project-URL: Maintainer, https://ahmedaljawahiry.com
Keywords: Django
Classifier: Framework :: Django :: 3.2
Classifier: Framework :: Django :: 4.0
Classifier: Framework :: Django :: 4.1
Classifier: Framework :: Django :: 4.2
Classifier: Framework :: Django :: 5.0
Classifier: Framework :: Django :: 5.1
Classifier: Intended Audience :: Developers
Classifier: License :: OSI Approved :: MIT License
Classifier: Operating System :: OS Independent
Classifier: Programming Language :: Python
Classifier: Programming Language :: Python :: 3
Classifier: Programming Language :: Python :: 3 :: Only
Classifier: Programming Language :: Python :: 3.7
Classifier: Programming Language :: Python :: 3.8
Classifier: Programming Language :: Python :: 3.9
Classifier: Programming Language :: Python :: 3.10
Classifier: Programming Language :: Python :: 3.11
Classifier: Programming Language :: Python :: 3.12
Requires-Python: >=3.7
License-File: LICENSE
Requires-Dist: django >=3.2
